china_cities/__init__.py
china_cities/cities.csv
china_cities/cities.py
china_cities-0.0.4.dist-info/LICENSE
china_cities-0.0.4.dist-info/METADATA
china_cities-0.0.4.dist-info/WHEEL
china_cities-0.0.4.dist-info/top_level.txt
china_cities-0.0.4.dist-info/RECORD
