Metadata-Version: 2.1
Name: china_cities
Version: 0.0.4
Summary: Python package to get the names of Chinese cities and provinces
Home-page: https://github.com/boeboe/china-cities
Author: Bart Van Bos
Author-email: bartvanbos@gmail.com
License: MIT
Keywords: china chinese cities provinces
Classifier: Development Status :: 5 - Production/Stable
Classifier: Intended Audience :: Developers
Classifier: Natural Language :: English
Classifier: License :: OSI Approved :: MIT License
Classifier: Programming Language :: Python
Classifier: Programming Language :: Python :: 3
Classifier: Topic :: Software Development :: Libraries :: Python Modules
Classifier: Topic :: System :: Software Distribution
License-File: LICENSE
